dissect/__init__.py
dissect/anchor.py
dissect/config.py
dissect/dataset_mapper.py
dissect/detector.py
dissect/finetune.py
dissect/head.py
dissect/loss.py
dissect/mask2adata.py
dissect/segmentation.py
dissect/swintransformer.py
dissect/test_time_augmentation.py
dissect/util/__init__.py
dissect/util/box_ops.py
dissect/util/colormap.py
dissect/util/misc.py
dissect/util/model_ema.py
dissect_st-0.5.4.dist-info/licenses/LICENSE
dissect_st-0.5.4.dist-info/METADATA
dissect_st-0.5.4.dist-info/WHEEL
dissect_st-0.5.4.dist-info/top_level.txt
dissect_st-0.5.4.dist-info/RECORD
