Metadata-Version: 2.4
Name: dissect-st
Version: 0.5.4
Summary: A Python package for accurate cell segmentation of spatial transcriptomics
Author: Yufeng Allen He
Author-email: Yufeng Allen He <yufenghepku@gmail.com>
License: MIT
Classifier: Programming Language :: Python :: 3
Classifier: Programming Language :: Python :: 3.7
Classifier: Programming Language :: Python :: 3.8
Classifier: Programming Language :: Python :: 3.9
Classifier: Programming Language :: Python :: 3.10
Classifier: License :: OSI Approved :: MIT License
Classifier: Operating System :: OS Independent
Requires-Python: >=3.7
License-File: LICENSE
Requires-Dist: numpy>=1.21.0
Requires-Dist: pandas>=1.3.0
Requires-Dist: scipy>=1.7.0
Requires-Dist: scikit-learn>=0.24.0
Requires-Dist: polars>=0.20.3
Requires-Dist: tifffile>=2023.12.9
Requires-Dist: anndata>=0.11.3
Requires-Dist: scikit-image>=0.25.2
Dynamic: license-file
